[
  {
    "doctorId": 1,
    "date": "2023-08-31",
    "hoursId": 61,
    "schedule": "2023-08-31T10:00:00Z"
  },
  {
    "doctorId": 1,
    "date": "2023-08-31",
    "hoursId": 64,
    "schedule": "2023-08-31T10:30:00Z"
  },
  {
    "doctorId": 1,
    "date": "2023-08-31",
    "hoursId": 67,
    "schedule": "2023-08-31T11:00:00Z"
  },
  {
    "doctorId": 1,
    "date": "2023-08-31",
    "hoursId": 70,
    "schedule": "2023-08-31T11:30:00Z"
  },
  {
    "doctorId": 1,
    "date": "2023-08-31",
    "hoursId": 73,
    "schedule": "2023-08-31T12:00:00Z"
  },
  {
    "doctorId": 1,
    "date": "2023-08-31",
    "hoursId": 76,
    "schedule": "2023-08-31T12:30:00Z"
  }
]